{"meta":{"version":1,"warehouse":"4.0.0"},"models":{"Asset":[{"_id":"themes/doflake/source/css/style.styl","path":"css/style.styl","modified":1,"renderable":1},{"_id":"themes/doflake/source/js/jquery.min.js","path":"js/jquery.min.js","modified":1,"renderable":1},{"_id":"themes/doflake/source/js/totop.js","path":"js/totop.js","modified":1,"renderable":1},{"_id":"themes/doflake/source/font/font-awesome-4.7.0/HELP-US-OUT.txt","path":"font/font-awesome-4.7.0/HELP-US-OUT.txt","modified":1,"renderable":1},{"_id":"themes/doflake/source/font/font-awesome-4.7.0/css/font-awesome.css","path":"font/font-awesome-4.7.0/css/font-awesome.css","modified":1,"renderable":1},{"_id":"themes/doflake/source/font/font-awesome-4.7.0/fonts/FontAwesome.otf","path":"font/font-awesome-4.7.0/fonts/FontAwesome.otf","modified":1,"renderable":1},{"_id":"themes/doflake/source/font/font-awesome-4.7.0/css/font-awesome.min.css","path":"font/font-awesome-4.7.0/css/font-awesome.min.css","modified":1,"renderable":1},{"_id":"themes/doflake/source/font/font-awesome-4.7.0/fonts/fontawesome-webfont.eot","path":"font/font-awesome-4.7.0/fonts/fontawesome-webfont.eot","modified":1,"renderable":1},{"_id":"themes/doflake/source/font/font-awesome-4.7.0/fonts/fontawesome-webfont.svg","path":"font/font-awesome-4.7.0/fonts/fontawesome-webfont.svg","modified":1,"renderable":1},{"_id":"themes/doflake/source/font/font-awesome-4.7.0/fonts/fontawesome-webfont.ttf","path":"font/font-awesome-4.7.0/fonts/fontawesome-webfont.ttf","modified":1,"renderable":1},{"_id":"themes/doflake/source/font/font-awesome-4.7.0/fonts/fontawesome-webfont.woff","path":"font/font-awesome-4.7.0/fonts/fontawesome-webfont.woff","modified":1,"renderable":1},{"_id":"themes/doflake/source/font/font-awesome-4.7.0/fonts/fontawesome-webfont.woff2","path":"font/font-awesome-4.7.0/fonts/fontawesome-webfont.woff2","modified":1,"renderable":1},{"_id":"themes/doflake/source/font/font-awesome-4.7.0/less/animated.less","path":"font/font-awesome-4.7.0/less/animated.less","modified":1,"renderable":1},{"_id":"themes/doflake/source/font/font-awesome-4.7.0/less/core.less","path":"font/font-awesome-4.7.0/less/core.less","modified":1,"renderable":1},{"_id":"themes/doflake/source/font/font-awesome-4.7.0/less/bordered-pulled.less","path":"font/font-awesome-4.7.0/less/bordered-pulled.less","modified":1,"renderable":1},{"_id":"themes/doflake/source/font/font-awesome-4.7.0/less/fixed-width.less","path":"font/font-awesome-4.7.0/less/fixed-width.less","modified":1,"renderable":1},{"_id":"themes/doflake/source/font/font-awesome-4.7.0/less/font-awesome.less","path":"font/font-awesome-4.7.0/less/font-awesome.less","modified":1,"renderable":1},{"_id":"themes/doflake/source/font/font-awesome-4.7.0/less/icons.less","path":"font/font-awesome-4.7.0/less/icons.less","modified":1,"renderable":1},{"_id":"themes/doflake/source/font/font-awesome-4.7.0/less/larger.less","path":"font/font-awesome-4.7.0/less/larger.less","modified":1,"renderable":1},{"_id":"themes/doflake/source/font/font-awesome-4.7.0/less/list.less","path":"font/font-awesome-4.7.0/less/list.less","modified":1,"renderable":1},{"_id":"themes/doflake/source/font/font-awesome-4.7.0/less/mixins.less","path":"font/font-awesome-4.7.0/less/mixins.less","modified":1,"renderable":1},{"_id":"themes/doflake/source/font/font-awesome-4.7.0/less/path.less","path":"font/font-awesome-4.7.0/less/path.less","modified":1,"renderable":1},{"_id":"themes/doflake/source/font/font-awesome-4.7.0/less/rotated-flipped.less","path":"font/font-awesome-4.7.0/less/rotated-flipped.less","modified":1,"renderable":1},{"_id":"themes/doflake/source/font/font-awesome-4.7.0/less/screen-reader.less","path":"font/font-awesome-4.7.0/less/screen-reader.less","modified":1,"renderable":1},{"_id":"themes/doflake/source/font/font-awesome-4.7.0/less/variables.less","path":"font/font-awesome-4.7.0/less/variables.less","modified":1,"renderable":1},{"_id":"themes/doflake/source/font/font-awesome-4.7.0/less/stacked.less","path":"font/font-awesome-4.7.0/less/stacked.less","modified":1,"renderable":1},{"_id":"themes/doflake/source/font/font-awesome-4.7.0/scss/font-awesome.scss","path":"font/font-awesome-4.7.0/scss/font-awesome.scss","modified":1,"renderable":1}],"Cache":[{"_id":"source/Funny-Baidu/index.md","hash":"d31123b9f65425f9f72e1c4f21f9951a0dfe3875","modified":1614774464493},{"_id":"source/_posts/[doflake] 主题文档 - 副本 (2).md","hash":"cd7086aaa3f1b9e44dbdf3756b6ac47fd1b1c3d6","modified":1620716195983},{"_id":"source/_posts/[doflake] 主题文档 - 副本 (4).md","hash":"cd7086aaa3f1b9e44dbdf3756b6ac47fd1b1c3d6","modified":1620716195983},{"_id":"source/_posts/[doflake] 主题文档 - 副本 (3).md","hash":"cd7086aaa3f1b9e44dbdf3756b6ac47fd1b1c3d6","modified":1620716195983},{"_id":"source/_posts/[doflake] 主题文档 - 副本 (6).md","hash":"cd7086aaa3f1b9e44dbdf3756b6ac47fd1b1c3d6","modified":1620716195983},{"_id":"source/_posts/[doflake] 主题文档 - 副本 (7).md","hash":"cd7086aaa3f1b9e44dbdf3756b6ac47fd1b1c3d6","modified":1620716195983},{"_id":"source/_posts/[doflake] 主题文档 - 副本 (5).md","hash":"cd7086aaa3f1b9e44dbdf3756b6ac47fd1b1c3d6","modified":1620716195983},{"_id":"source/_posts/[doflake] 主题文档 - 副本 (8).md","hash":"cd7086aaa3f1b9e44dbdf3756b6ac47fd1b1c3d6","modified":1620716195983},{"_id":"source/_posts/[doflake] 主题文档 - 副本.md","hash":"cd7086aaa3f1b9e44dbdf3756b6ac47fd1b1c3d6","modified":1620716195983},{"_id":"source/_posts/[doflake] 主题文档.md","hash":"cd7086aaa3f1b9e44dbdf3756b6ac47fd1b1c3d6","modified":1620810583413},{"_id":"themes/doflake/README.md","hash":"eae972ab0a5e30cd2514b8d94a38f640ba202718","modified":1614774464539},{"_id":"themes/doflake/_config.yml","hash":"bd5368b3c4a4b811e685e85b240cfbd5303d85c9","modified":1620811843906},{"_id":"themes/doflake/languages/default.yml","hash":"ecd1b1ab0ceba9f68e6a1e54ef058186f8fb6d37","modified":1614774464540},{"_id":"themes/doflake/languages/en.yml","hash":"ecd1b1ab0ceba9f68e6a1e54ef058186f8fb6d37","modified":1614774464540},{"_id":"themes/doflake/layout/index.ejs","hash":"dd2ffcc874e21635bddf23e875215396531c7a75","modified":1620807893610},{"_id":"themes/doflake/languages/zh-CN.yml","hash":"85f9505cba1839f05263ff44c6404f230e75c4df","modified":1614774464540},{"_id":"themes/doflake/layout/archive.ejs","hash":"1095e1f337e042db52cdd8136e8a26f771bb79b4","modified":1617626471493},{"_id":"themes/doflake/layout/post.ejs","hash":"7d50943922035e3d75ed803879f84f26a829e4e0","modified":1615293857433},{"_id":"themes/doflake/layout/layout.ejs","hash":"20f9db757c0cd3328ee8c269461453ec2f3370ab","modified":1620803221269},{"_id":"themes/doflake/layout/_meta/totop.ejs","hash":"b2f493c956f399bacbab340f438c16eb9c173d5c","modified":1614774464541},{"_id":"themes/doflake/layout/_basic/mathjax.ejs","hash":"282e437fa36fdb6d2e538e542411dc8b14f87a45","modified":1614774464540},{"_id":"themes/doflake/source/css/style.styl","hash":"ad29d532e8bbf04e81abfe86096fe2be623f11ad","modified":1617626184092},{"_id":"themes/doflake/layout/_meta/clock.ejs","hash":"7afbf59548a86010edc996e5e73db1db0965f4bf","modified":1614774464541},{"_id":"themes/doflake/source/js/totop.js","hash":"c84ca73192007612f9435884315d04a38f213758","modified":1614774464564},{"_id":"themes/doflake/source/css/_basic/card.styl","hash":"cb053c60520a7fe56d437ce74d9506711663a130","modified":1620802176918},{"_id":"themes/doflake/source/css/_basic/hljs.styl","hash":"dee7472ada7920620f26111573a303e9838edf0b","modified":1614774464543},{"_id":"themes/doflake/source/css/_basic/index.styl","hash":"0ef94dd7a9f9f133827268eeb2c25dea4581d437","modified":1617624317439},{"_id":"themes/doflake/source/css/_layout/body.styl","hash":"6758be2160b0bedde314b4fa032713bfe6434d27","modified":1620812093225},{"_id":"themes/doflake/source/css/_layout/index.styl","hash":"1fb64ee1b13cf0df2998c188cdeb033f5fad409e","modified":1617626152362},{"_id":"themes/doflake/source/css/_markdown/gutter.styl","hash":"7199235668ed289ad3bd14c6beb63294d6077953","modified":1614774464544},{"_id":"themes/doflake/source/css/_markdown/hljs.styl","hash":"47306d9960aae5138d6d4a750eff3dc2eadf2eea","modified":1614774464545},{"_id":"themes/doflake/source/css/_markdown/index.styl","hash":"0b69f3691db36db10319a7e768591110419a11d5","modified":1614774464545},{"_id":"themes/doflake/source/css/_markdown/table.styl","hash":"d9b3d7869832bb8b1433a84b51ee73804114ff74","modified":1614774464545},{"_id":"themes/doflake/source/css/_meta/clock.styl","hash":"abefc2b3cfa5dd9d942a2d52e018f94bbd3a0c54","modified":1614774464545},{"_id":"themes/doflake/source/css/_meta/index.styl","hash":"ca291b6eb8d82294f6a251d88895dcb8d0f41869","modified":1614774464545},{"_id":"themes/doflake/source/css/_partial/archive.styl","hash":"fd944d85d23382f62d2e25805ff52aaf83a12dd4","modified":1614774464546},{"_id":"themes/doflake/source/css/_partial/body.styl","hash":"2f86ac63a0ce72ad79779e9fa0b1867154e3deef","modified":1617626418211},{"_id":"themes/doflake/source/css/_partial/header.styl","hash":"c4c00bf60ca8c2573d78f4204a92c31ebb3cb59d","modified":1614774464546},{"_id":"themes/doflake/source/css/_partial/index.styl","hash":"48089b44581be5cade513ee0b9ac706a90294752","modified":1617622565155},{"_id":"themes/doflake/source/css/_partial/post.styl","hash":"21b60908950a96379b41df39278564158793ebfe","modified":1620811832457},{"_id":"themes/doflake/source/font/font-awesome-4.7.0/HELP-US-OUT.txt","hash":"ee33b2798b1e714b904d663436c6b3521011d1fa","modified":1614774464547},{"_id":"themes/doflake/source/font/font-awesome-4.7.0/css/font-awesome.css","hash":"3655f1fdf1e584c4d8e8d39026093ca306a5a341","modified":1614774464548},{"_id":"themes/doflake/source/font/font-awesome-4.7.0/css/font-awesome.min.css","hash":"88af80502c44cd52ca81ffe7dc7276b7eccb06cf","modified":1614774464548},{"_id":"themes/doflake/source/font/font-awesome-4.7.0/less/animated.less","hash":"472ec14f388c90a7201861e77faec317d038fd9c","modified":1614774464557},{"_id":"themes/doflake/source/font/font-awesome-4.7.0/less/core.less","hash":"5f436a1afd7f1de7dde20ed8c2fd84812b8acf12","modified":1614774464557},{"_id":"themes/doflake/source/font/font-awesome-4.7.0/less/bordered-pulled.less","hash":"66dc98ad0e4151e8938350f1ee3d0932348b37e8","modified":1614774464557},{"_id":"themes/doflake/source/font/font-awesome-4.7.0/less/fixed-width.less","hash":"a9552c8a91766a6d926c43c4c0f74acb62aaf719","modified":1614774464558},{"_id":"themes/doflake/source/font/font-awesome-4.7.0/less/font-awesome.less","hash":"06bd9cd5c5a646b1c631ba7b1edb77f60d84a91b","modified":1614774464558},{"_id":"themes/doflake/source/font/font-awesome-4.7.0/less/icons.less","hash":"e7492081853b880643f96e28659218b92c6e660a","modified":1614774464559},{"_id":"themes/doflake/source/font/font-awesome-4.7.0/less/larger.less","hash":"d9610d7f83b0aaf3fdd5fa048117bd8620adf346","modified":1614774464559},{"_id":"themes/doflake/source/font/font-awesome-4.7.0/less/list.less","hash":"2b203f3bacd6eaa58d0aa11efb9fb661b884eeb9","modified":1614774464559},{"_id":"themes/doflake/source/font/font-awesome-4.7.0/less/mixins.less","hash":"9b53403a944d93c5d7238c8942534fccf7957cff","modified":1614774464559},{"_id":"themes/doflake/source/font/font-awesome-4.7.0/less/path.less","hash":"fce36570fe54da40c1c61f20d62bf9751a81a27e","modified":1614774464559},{"_id":"themes/doflake/source/font/font-awesome-4.7.0/less/rotated-flipped.less","hash":"39ec6a3d98e5a55a2330935d139f95855c139dcf","modified":1614774464559},{"_id":"themes/doflake/source/font/font-awesome-4.7.0/less/screen-reader.less","hash":"3fa86249735534461a08afa86b5d7d774de7ef3f","modified":1614774464560},{"_id":"themes/doflake/source/font/font-awesome-4.7.0/less/variables.less","hash":"e0dab04318d43211435c82989fbc05d0876b2708","modified":1614774464560},{"_id":"themes/doflake/source/font/font-awesome-4.7.0/less/stacked.less","hash":"ee10b7a0bc941f8d0bbd092d4178b9fae9f1661f","modified":1614774464560},{"_id":"themes/doflake/source/font/font-awesome-4.7.0/scss/_animated.scss","hash":"c3d081abee1076d36a289afc6488e676bc59f023","modified":1614774464560},{"_id":"themes/doflake/source/font/font-awesome-4.7.0/scss/_bordered-pulled.scss","hash":"39353047bbcce4f3f706666df1547e64546932a0","modified":1614774464561},{"_id":"themes/doflake/source/font/font-awesome-4.7.0/scss/_core.scss","hash":"2dce8814642ef0ee86c65f3d29818c17fd8951f9","modified":1614774464561},{"_id":"themes/doflake/source/font/font-awesome-4.7.0/scss/_fixed-width.scss","hash":"f4af333866ff3c0da59493fc7077965c6e9d46ac","modified":1614774464561},{"_id":"themes/doflake/source/font/font-awesome-4.7.0/scss/_larger.scss","hash":"c5cf379c23025aa001f850bd560a87a92e4f711d","modified":1614774464562},{"_id":"themes/doflake/source/font/font-awesome-4.7.0/scss/_icons.scss","hash":"303a6e9e04e91a132612f094b34cccfc90c63bec","modified":1614774464561},{"_id":"themes/doflake/source/font/font-awesome-4.7.0/scss/_list.scss","hash":"8e9c5708bd91364a749f93555ba65af3c49ff1a6","modified":1614774464562},{"_id":"themes/doflake/source/font/font-awesome-4.7.0/scss/_mixins.scss","hash":"25b2361e654e3512c1f6024f3a8d593413611a58","modified":1614774464562},{"_id":"themes/doflake/source/font/font-awesome-4.7.0/scss/_path.scss","hash":"011339ce07bb12a5736edd7fdbed0b7f3c63bf72","modified":1614774464562},{"_id":"themes/doflake/source/font/font-awesome-4.7.0/scss/_rotated-flipped.scss","hash":"fd48d098af52ffff6f829e7f5a2250a9c3cfc87f","modified":1614774464562},{"_id":"themes/doflake/source/font/font-awesome-4.7.0/scss/_screen-reader.scss","hash":"ebe3fe40059e5a2a3a3c0c0f587a2e2bc23fd1b2","modified":1614774464563},{"_id":"themes/doflake/source/font/font-awesome-4.7.0/scss/_stacked.scss","hash":"c4fe90e7781e8b229bf2657312ba61ecf1026cab","modified":1614774464563},{"_id":"themes/doflake/source/font/font-awesome-4.7.0/scss/_variables.scss","hash":"8e450f7064c308a124fe82ded322db59fbbeb59f","modified":1614774464563},{"_id":"themes/doflake/source/font/font-awesome-4.7.0/scss/font-awesome.scss","hash":"6bfc7e75fd344628b06d85f7fa4d48b106334584","modified":1614774464563},{"_id":"themes/doflake/source/js/jquery.min.js","hash":"b063d0aa57f0c50d9bfb9895b76a9467155df7f1","modified":1614774464564},{"_id":"themes/doflake/source/font/font-awesome-4.7.0/fonts/fontawesome-webfont.woff","hash":"28b782240b3e76db824e12c02754a9731a167527","modified":1614774464556},{"_id":"themes/doflake/source/font/font-awesome-4.7.0/fonts/fontawesome-webfont.woff2","hash":"d6f48cba7d076fb6f2fd6ba993a75b9dc1ecbf0c","modified":1614774464557},{"_id":"themes/doflake/source/font/font-awesome-4.7.0/fonts/FontAwesome.otf","hash":"048707bc52ac4b6563aaa383bfe8660a0ddc908c","modified":1614774464550},{"_id":"themes/doflake/source/font/font-awesome-4.7.0/fonts/fontawesome-webfont.ttf","hash":"13b1eab65a983c7a73bc7997c479d66943f7c6cb","modified":1614774464555},{"_id":"themes/doflake/source/font/font-awesome-4.7.0/fonts/fontawesome-webfont.eot","hash":"d980c2ce873dc43af460d4d572d441304499f400","modified":1614774464551},{"_id":"themes/doflake/source/font/font-awesome-4.7.0/fonts/fontawesome-webfont.svg","hash":"b5483b11f8ba213e733b5b8af9927a04fec996f6","modified":1614774464554},{"_id":"themes/doflake/layout/_partial/card.ejs","hash":"4517755f66981acfa8a92ed27d9ebf0e1266641d","modified":1620802037719},{"_id":"themes/doflake/layout/_partial/head.ejs","hash":"e8879ca1616a7e664546f34ef86398c7dfa386d2","modified":1620803217030},{"_id":"public/Funny-Baidu/index.html","hash":"ea36ce1bdb84345baa5106c1ef9dcd4b2b62885b","modified":1620812122642},{"_id":"public/atom.xml","hash":"24007dfe719f543f1e196a2dcb3f24cc33698b3f","modified":1620812122642},{"_id":"public/Doflake/Document/index.html","hash":"15640bc4a313e032e1d698ff528e0db18d7eae3e","modified":1620812122642},{"_id":"public/archives/index.html","hash":"331e32cfa01a09b7fe5b7d928039b4ae7cca0eb7","modified":1620812122642},{"_id":"public/archives/2021/index.html","hash":"331e32cfa01a09b7fe5b7d928039b4ae7cca0eb7","modified":1620812122642},{"_id":"public/archives/2021/03/index.html","hash":"331e32cfa01a09b7fe5b7d928039b4ae7cca0eb7","modified":1620812122642},{"_id":"public/index.html","hash":"d220cd43bfdb7f73c4bdf38feb4c96ce2de1a80c","modified":1620812122642},{"_id":"public/font/font-awesome-4.7.0/HELP-US-OUT.txt","hash":"ee33b2798b1e714b904d663436c6b3521011d1fa","modified":1620812122642},{"_id":"public/font/font-awesome-4.7.0/less/core.less","hash":"5f436a1afd7f1de7dde20ed8c2fd84812b8acf12","modified":1620812122642},{"_id":"public/font/font-awesome-4.7.0/less/animated.less","hash":"472ec14f388c90a7201861e77faec317d038fd9c","modified":1620812122642},{"_id":"public/font/font-awesome-4.7.0/less/bordered-pulled.less","hash":"66dc98ad0e4151e8938350f1ee3d0932348b37e8","modified":1620812122642},{"_id":"public/font/font-awesome-4.7.0/less/fixed-width.less","hash":"a9552c8a91766a6d926c43c4c0f74acb62aaf719","modified":1620812122642},{"_id":"public/font/font-awesome-4.7.0/less/font-awesome.less","hash":"06bd9cd5c5a646b1c631ba7b1edb77f60d84a91b","modified":1620812122642},{"_id":"public/font/font-awesome-4.7.0/less/larger.less","hash":"d9610d7f83b0aaf3fdd5fa048117bd8620adf346","modified":1620812122642},{"_id":"public/font/font-awesome-4.7.0/less/icons.less","hash":"e7492081853b880643f96e28659218b92c6e660a","modified":1620812122642},{"_id":"public/font/font-awesome-4.7.0/less/list.less","hash":"2b203f3bacd6eaa58d0aa11efb9fb661b884eeb9","modified":1620812122642},{"_id":"public/font/font-awesome-4.7.0/less/mixins.less","hash":"9b53403a944d93c5d7238c8942534fccf7957cff","modified":1620812122642},{"_id":"public/font/font-awesome-4.7.0/less/path.less","hash":"fce36570fe54da40c1c61f20d62bf9751a81a27e","modified":1620812122642},{"_id":"public/font/font-awesome-4.7.0/less/rotated-flipped.less","hash":"39ec6a3d98e5a55a2330935d139f95855c139dcf","modified":1620812122642},{"_id":"public/font/font-awesome-4.7.0/less/screen-reader.less","hash":"3fa86249735534461a08afa86b5d7d774de7ef3f","modified":1620812122642},{"_id":"public/font/font-awesome-4.7.0/less/variables.less","hash":"e0dab04318d43211435c82989fbc05d0876b2708","modified":1620812122642},{"_id":"public/font/font-awesome-4.7.0/less/stacked.less","hash":"ee10b7a0bc941f8d0bbd092d4178b9fae9f1661f","modified":1620812122642},{"_id":"public/font/font-awesome-4.7.0/scss/font-awesome.scss","hash":"6bfc7e75fd344628b06d85f7fa4d48b106334584","modified":1620812122642},{"_id":"public/font/font-awesome-4.7.0/fonts/fontawesome-webfont.woff","hash":"28b782240b3e76db824e12c02754a9731a167527","modified":1620812122642},{"_id":"public/font/font-awesome-4.7.0/fonts/fontawesome-webfont.woff2","hash":"d6f48cba7d076fb6f2fd6ba993a75b9dc1ecbf0c","modified":1620812122642},{"_id":"public/font/font-awesome-4.7.0/fonts/FontAwesome.otf","hash":"048707bc52ac4b6563aaa383bfe8660a0ddc908c","modified":1620812122642},{"_id":"public/font/font-awesome-4.7.0/fonts/fontawesome-webfont.ttf","hash":"13b1eab65a983c7a73bc7997c479d66943f7c6cb","modified":1620812122642},{"_id":"public/css/style.css","hash":"32e416064d18dc4fa84d2bb1bf4888597c50c949","modified":1620812122642},{"_id":"public/js/totop.js","hash":"5c133d783da251d5a5b85059707ec9b3afec6ef7","modified":1620812122642},{"_id":"public/font/font-awesome-4.7.0/fonts/fontawesome-webfont.eot","hash":"d980c2ce873dc43af460d4d572d441304499f400","modified":1620812122642},{"_id":"public/font/font-awesome-4.7.0/css/font-awesome.min.css","hash":"512c7d79033e3028a9be61b540cf1a6870c896f8","modified":1620812122642},{"_id":"public/font/font-awesome-4.7.0/css/font-awesome.css","hash":"0140952c64e3f2b74ef64e050f2fe86eab6624c8","modified":1620812122642},{"_id":"public/js/jquery.min.js","hash":"aabcbfcd1332e741704318fede8e4c6893245266","modified":1620812122642},{"_id":"public/font/font-awesome-4.7.0/fonts/fontawesome-webfont.svg","hash":"b5483b11f8ba213e733b5b8af9927a04fec996f6","modified":1620812122642}],"Category":[],"Data":[],"Page":[{"layout":"false","_content":"{%raw%}\n<!DOCTYPE html>\n<html xmlns=\"http://www.w3.org/1999/xhtml\">\n  <head>\n    <meta charset=\"utf-8\" />\n    <meta name=\"renderer\" content=\"webkit\" />\n    <meta http-equiv=\"X-UA-Compatible\" content=\"IE=edge\" />\n    <meta http-equiv=\"Cache-Control\" content=\"no-transform\" />\n    <meta http-equiv=\"Cache-Control\" content=\"no-siteapp\" />\n    <meta name=\"viewport\" content=\"width=device-width, initial-scale=1\" />\n\n    <title>让我帮你百度一下 | Let Me Baidu That For You</title>\n\n    <link\n      rel=\"shortcut icon\"\n      href=\"https://cdn.jsdelivr.net/gh/heson525/heson-demo/baidu/favicon.ico\"\n    />\n    <link\n      rel=\"stylesheet\"\n      href=\"https://cdn.jsdelivr.net/gh/heson525/heson-demo/baidu/css/style.css\"\n    />\n\n    <script src=\"https://cdn.jsdelivr.net/gh/heson525/heson-demo/baidu/js/jquery.min.js\"></script>\n    <script src=\"https://cdn.jsdelivr.net/gh/heson525/heson-demo/baidu/js/base64.min.js\"></script>\n    <script src=\"https://cdn.jsdelivr.net/gh/heson525/heson-demo/baidu/js/clipboard.min.js\"></script>\n    <script src=\"https://cdn.jsdelivr.net/gh/heson525/heson-demo/baidu/js/script.js\"></script>\n  </head>\n  <body>\n    <section id=\"search\">\n      <div class=\"search-header\">\n        <h2>\n          <span class=\"let-me\">让我帮你</span>\n          <img\n            src=\"https://cdn.jsdelivr.net/gh/heson525/heson-demo/baidu/img/baidu_logo.png\"\n            alt=\"百度\"\n            title=\"让我帮你百度一下\"\n          />\n          <span class=\"for-you\">一下</span>\n        </h2>\n      </div>\n\n      <form id=\"search-form\">\n        <div class=\"search-form-group\">\n          <div class=\"search-form-input\">\n            <input\n              type=\"search\"\n              id=\"kw\"\n              maxlength=\"255\"\n              autocomplete=\"off\"\n              required\n            />\n          </div>\n          <button id=\"search-submit\">百度一下</button>\n        </div>\n      </form>\n    </section>\n\n    <section id=\"function\">\n      <p id=\"tips\">输入一个问题，然后点击百度一下</p>\n\n      <button id=\"stop\">快停下！我是自己人</button>\n\n      <div id=\"output\">\n        <textarea id=\"url-output\" rows=\"3\" readonly></textarea>\n        <div class=\"tool-btns\">\n          <button data-clipboard-target=\"#url-output\">复制</button>\n          <button id=\"preview\">预览</button>\n        </div>\n      </div>\n    </section>\n\n    <footer id=\"footer\">\n      <ul class=\"footer-right\">\n        <li>\n          * 本站与百度公司没有任何联系，baidu 以及本站出现的百度公司 Logo\n          是百度公司的商标\n        </li>\n      </ul>\n    </footer>\n\n    <div id=\"arrow\"></div>\n  </body>\n</html>\n{%endraw%}","source":"Funny-Baidu/index.md","raw":"---\nlayout: false\n---\n{%raw%}\n<!DOCTYPE html>\n<html xmlns=\"http://www.w3.org/1999/xhtml\">\n  <head>\n    <meta charset=\"utf-8\" />\n    <meta name=\"renderer\" content=\"webkit\" />\n    <meta http-equiv=\"X-UA-Compatible\" content=\"IE=edge\" />\n    <meta http-equiv=\"Cache-Control\" content=\"no-transform\" />\n    <meta http-equiv=\"Cache-Control\" content=\"no-siteapp\" />\n    <meta name=\"viewport\" content=\"width=device-width, initial-scale=1\" />\n\n    <title>让我帮你百度一下 | Let Me Baidu That For You</title>\n\n    <link\n      rel=\"shortcut icon\"\n      href=\"https://cdn.jsdelivr.net/gh/heson525/heson-demo/baidu/favicon.ico\"\n    />\n    <link\n      rel=\"stylesheet\"\n      href=\"https://cdn.jsdelivr.net/gh/heson525/heson-demo/baidu/css/style.css\"\n    />\n\n    <script src=\"https://cdn.jsdelivr.net/gh/heson525/heson-demo/baidu/js/jquery.min.js\"></script>\n    <script src=\"https://cdn.jsdelivr.net/gh/heson525/heson-demo/baidu/js/base64.min.js\"></script>\n    <script src=\"https://cdn.jsdelivr.net/gh/heson525/heson-demo/baidu/js/clipboard.min.js\"></script>\n    <script src=\"https://cdn.jsdelivr.net/gh/heson525/heson-demo/baidu/js/script.js\"></script>\n  </head>\n  <body>\n    <section id=\"search\">\n      <div class=\"search-header\">\n        <h2>\n          <span class=\"let-me\">让我帮你</span>\n          <img\n            src=\"https://cdn.jsdelivr.net/gh/heson525/heson-demo/baidu/img/baidu_logo.png\"\n            alt=\"百度\"\n            title=\"让我帮你百度一下\"\n          />\n          <span class=\"for-you\">一下</span>\n        </h2>\n      </div>\n\n      <form id=\"search-form\">\n        <div class=\"search-form-group\">\n          <div class=\"search-form-input\">\n            <input\n              type=\"search\"\n              id=\"kw\"\n              maxlength=\"255\"\n              autocomplete=\"off\"\n              required\n            />\n          </div>\n          <button id=\"search-submit\">百度一下</button>\n        </div>\n      </form>\n    </section>\n\n    <section id=\"function\">\n      <p id=\"tips\">输入一个问题，然后点击百度一下</p>\n\n      <button id=\"stop\">快停下！我是自己人</button>\n\n      <div id=\"output\">\n        <textarea id=\"url-output\" rows=\"3\" readonly></textarea>\n        <div class=\"tool-btns\">\n          <button data-clipboard-target=\"#url-output\">复制</button>\n          <button id=\"preview\">预览</button>\n        </div>\n      </div>\n    </section>\n\n    <footer id=\"footer\">\n      <ul class=\"footer-right\">\n        <li>\n          * 本站与百度公司没有任何联系，baidu 以及本站出现的百度公司 Logo\n          是百度公司的商标\n        </li>\n      </ul>\n    </footer>\n\n    <div id=\"arrow\"></div>\n  </body>\n</html>\n{%endraw%}","date":"2021-03-10T12:02:22.978Z","updated":"2021-03-03T12:27:44.493Z","path":"Funny-Baidu/index.html","title":"","comments":1,"_id":"ckol9ou6q0000d0avacby8lf8","content":"\n<!DOCTYPE html>\n<html xmlns=\"http://www.w3.org/1999/xhtml\">\n  <head>\n    <meta charset=\"utf-8\" />\n    <meta name=\"renderer\" content=\"webkit\" />\n    <meta http-equiv=\"X-UA-Compatible\" content=\"IE=edge\" />\n    <meta http-equiv=\"Cache-Control\" content=\"no-transform\" />\n    <meta http-equiv=\"Cache-Control\" content=\"no-siteapp\" />\n    <meta name=\"viewport\" content=\"width=device-width, initial-scale=1\" />\n\n    <title>让我帮你百度一下 | Let Me Baidu That For You</title>\n\n    <link\n      rel=\"shortcut icon\"\n      href=\"https://cdn.jsdelivr.net/gh/heson525/heson-demo/baidu/favicon.ico\"\n    />\n    <link\n      rel=\"stylesheet\"\n      href=\"https://cdn.jsdelivr.net/gh/heson525/heson-demo/baidu/css/style.css\"\n    />\n\n    <script src=\"https://cdn.jsdelivr.net/gh/heson525/heson-demo/baidu/js/jquery.min.js\"></script>\n    <script src=\"https://cdn.jsdelivr.net/gh/heson525/heson-demo/baidu/js/base64.min.js\"></script>\n    <script src=\"https://cdn.jsdelivr.net/gh/heson525/heson-demo/baidu/js/clipboard.min.js\"></script>\n    <script src=\"https://cdn.jsdelivr.net/gh/heson525/heson-demo/baidu/js/script.js\"></script>\n  </head>\n  <body>\n    <section id=\"search\">\n      <div class=\"search-header\">\n        <h2>\n          <span class=\"let-me\">让我帮你</span>\n          <img\n            src=\"https://cdn.jsdelivr.net/gh/heson525/heson-demo/baidu/img/baidu_logo.png\"\n            alt=\"百度\"\n            title=\"让我帮你百度一下\"\n          />\n          <span class=\"for-you\">一下</span>\n        </h2>\n      </div>\n\n      <form id=\"search-form\">\n        <div class=\"search-form-group\">\n          <div class=\"search-form-input\">\n            <input\n              type=\"search\"\n              id=\"kw\"\n              maxlength=\"255\"\n              autocomplete=\"off\"\n              required\n            />\n          </div>\n          <button id=\"search-submit\">百度一下</button>\n        </div>\n      </form>\n    </section>\n\n    <section id=\"function\">\n      <p id=\"tips\">输入一个问题，然后点击百度一下</p>\n\n      <button id=\"stop\">快停下！我是自己人</button>\n\n      <div id=\"output\">\n        <textarea id=\"url-output\" rows=\"3\" readonly></textarea>\n        <div class=\"tool-btns\">\n          <button data-clipboard-target=\"#url-output\">复制</button>\n          <button id=\"preview\">预览</button>\n        </div>\n      </div>\n    </section>\n\n    <footer id=\"footer\">\n      <ul class=\"footer-right\">\n        <li>\n          * 本站与百度公司没有任何联系，baidu 以及本站出现的百度公司 Logo\n          是百度公司的商标\n        </li>\n      </ul>\n    </footer>\n\n    <div id=\"arrow\"></div>\n  </body>\n</html>\n","site":{"data":{}},"excerpt":"","more":"\n<!DOCTYPE html>\n<html xmlns=\"http://www.w3.org/1999/xhtml\">\n  <head>\n    <meta charset=\"utf-8\" />\n    <meta name=\"renderer\" content=\"webkit\" />\n    <meta http-equiv=\"X-UA-Compatible\" content=\"IE=edge\" />\n    <meta http-equiv=\"Cache-Control\" content=\"no-transform\" />\n    <meta http-equiv=\"Cache-Control\" content=\"no-siteapp\" />\n    <meta name=\"viewport\" content=\"width=device-width, initial-scale=1\" />\n\n    <title>让我帮你百度一下 | Let Me Baidu That For You</title>\n\n    <link\n      rel=\"shortcut icon\"\n      href=\"https://cdn.jsdelivr.net/gh/heson525/heson-demo/baidu/favicon.ico\"\n    />\n    <link\n      rel=\"stylesheet\"\n      href=\"https://cdn.jsdelivr.net/gh/heson525/heson-demo/baidu/css/style.css\"\n    />\n\n    <script src=\"https://cdn.jsdelivr.net/gh/heson525/heson-demo/baidu/js/jquery.min.js\"></script>\n    <script src=\"https://cdn.jsdelivr.net/gh/heson525/heson-demo/baidu/js/base64.min.js\"></script>\n    <script src=\"https://cdn.jsdelivr.net/gh/heson525/heson-demo/baidu/js/clipboard.min.js\"></script>\n    <script src=\"https://cdn.jsdelivr.net/gh/heson525/heson-demo/baidu/js/script.js\"></script>\n  </head>\n  <body>\n    <section id=\"search\">\n      <div class=\"search-header\">\n        <h2>\n          <span class=\"let-me\">让我帮你</span>\n          <img\n            src=\"https://cdn.jsdelivr.net/gh/heson525/heson-demo/baidu/img/baidu_logo.png\"\n            alt=\"百度\"\n            title=\"让我帮你百度一下\"\n          />\n          <span class=\"for-you\">一下</span>\n        </h2>\n      </div>\n\n      <form id=\"search-form\">\n        <div class=\"search-form-group\">\n          <div class=\"search-form-input\">\n            <input\n              type=\"search\"\n              id=\"kw\"\n              maxlength=\"255\"\n              autocomplete=\"off\"\n              required\n            />\n          </div>\n          <button id=\"search-submit\">百度一下</button>\n        </div>\n      </form>\n    </section>\n\n    <section id=\"function\">\n      <p id=\"tips\">输入一个问题，然后点击百度一下</p>\n\n      <button id=\"stop\">快停下！我是自己人</button>\n\n      <div id=\"output\">\n        <textarea id=\"url-output\" rows=\"3\" readonly></textarea>\n        <div class=\"tool-btns\">\n          <button data-clipboard-target=\"#url-output\">复制</button>\n          <button id=\"preview\">预览</button>\n        </div>\n      </div>\n    </section>\n\n    <footer id=\"footer\">\n      <ul class=\"footer-right\">\n        <li>\n          * 本站与百度公司没有任何联系，baidu 以及本站出现的百度公司 Logo\n          是百度公司的商标\n        </li>\n      </ul>\n    </footer>\n\n    <div id=\"arrow\"></div>\n  </body>\n</html>\n"}],"Post":[{"title":"【Doflake】 主题文档","mathjax":true,"date":"2021-03-10T12:02:26.000Z","link_c":"Doflake","link_name":"Document","top":null,"headimg":"https://cdn.jsdelivr.net/gh/doflake/Picture/Posts/doflake-document/HeadImg.jpg","_content":"","source":"_posts/[doflake] 主题文档 - 副本 (2).md","raw":"---\ntitle: '【Doflake】 主题文档'\nmathjax: true\ndate: 2021-03-10 20:02:26\nlink_c: Doflake\nlink_name: Document\ntop:\nheadimg: https://cdn.jsdelivr.net/gh/doflake/Picture/Posts/doflake-document/HeadImg.jpg\n---\n","slug":"[doflake] 主题文档 - 副本 (2)","published":1,"updated":"2021-05-11T06:56:35.983Z","comments":1,"layout":"post","photos":[],"link":"","_id":"ckol9ou6s0001d0av7v1aczxs","content":"","site":{"data":{}},"excerpt":"","more":""},{"title":"【Doflake】 主题文档","mathjax":true,"date":"2021-03-10T12:02:26.000Z","link_c":"Doflake","link_name":"Document","top":null,"headimg":"https://cdn.jsdelivr.net/gh/doflake/Picture/Posts/doflake-document/HeadImg.jpg","_content":"","source":"_posts/[doflake] 主题文档 - 副本 (4).md","raw":"---\ntitle: '【Doflake】 主题文档'\nmathjax: true\ndate: 2021-03-10 20:02:26\nlink_c: Doflake\nlink_name: Document\ntop:\nheadimg: https://cdn.jsdelivr.net/gh/doflake/Picture/Posts/doflake-document/HeadImg.jpg\n---\n","slug":"[doflake] 主题文档 - 副本 (4)","published":1,"updated":"2021-05-11T06:56:35.983Z","comments":1,"layout":"post","photos":[],"link":"","_id":"ckol9ou6u0002d0av872h3gwy","content":"","site":{"data":{}},"excerpt":"","more":""},{"title":"【Doflake】 主题文档","mathjax":true,"date":"2021-03-10T12:02:26.000Z","link_c":"Doflake","link_name":"Document","top":null,"headimg":"https://cdn.jsdelivr.net/gh/doflake/Picture/Posts/doflake-document/HeadImg.jpg","_content":"","source":"_posts/[doflake] 主题文档 - 副本 (3).md","raw":"---\ntitle: '【Doflake】 主题文档'\nmathjax: true\ndate: 2021-03-10 20:02:26\nlink_c: Doflake\nlink_name: Document\ntop:\nheadimg: https://cdn.jsdelivr.net/gh/doflake/Picture/Posts/doflake-document/HeadImg.jpg\n---\n","slug":"[doflake] 主题文档 - 副本 (3)","published":1,"updated":"2021-05-11T06:56:35.983Z","comments":1,"layout":"post","photos":[],"link":"","_id":"ckol9ou6v0003d0av1et9c09r","content":"","site":{"data":{}},"excerpt":"","more":""},{"title":"【Doflake】 主题文档","mathjax":true,"date":"2021-03-10T12:02:26.000Z","link_c":"Doflake","link_name":"Document","top":null,"headimg":"https://cdn.jsdelivr.net/gh/doflake/Picture/Posts/doflake-document/HeadImg.jpg","_content":"","source":"_posts/[doflake] 主题文档 - 副本 (6).md","raw":"---\ntitle: '【Doflake】 主题文档'\nmathjax: true\ndate: 2021-03-10 20:02:26\nlink_c: Doflake\nlink_name: Document\ntop:\nheadimg: https://cdn.jsdelivr.net/gh/doflake/Picture/Posts/doflake-document/HeadImg.jpg\n---\n","slug":"[doflake] 主题文档 - 副本 (6)","published":1,"updated":"2021-05-11T06:56:35.983Z","comments":1,"layout":"post","photos":[],"link":"","_id":"ckol9ou6w0004d0av0ytp3x8y","content":"","site":{"data":{}},"excerpt":"","more":""},{"title":"【Doflake】 主题文档","mathjax":true,"date":"2021-03-10T12:02:26.000Z","link_c":"Doflake","link_name":"Document","top":null,"headimg":"https://cdn.jsdelivr.net/gh/doflake/Picture/Posts/doflake-document/HeadImg.jpg","_content":"","source":"_posts/[doflake] 主题文档 - 副本 (7).md","raw":"---\ntitle: '【Doflake】 主题文档'\nmathjax: true\ndate: 2021-03-10 20:02:26\nlink_c: Doflake\nlink_name: Document\ntop:\nheadimg: https://cdn.jsdelivr.net/gh/doflake/Picture/Posts/doflake-document/HeadImg.jpg\n---\n","slug":"[doflake] 主题文档 - 副本 (7)","published":1,"updated":"2021-05-11T06:56:35.983Z","comments":1,"layout":"post","photos":[],"link":"","_id":"ckol9ou6w0005d0avf4rb3beq","content":"","site":{"data":{}},"excerpt":"","more":""},{"title":"【Doflake】 主题文档","mathjax":true,"date":"2021-03-10T12:02:26.000Z","link_c":"Doflake","link_name":"Document","top":null,"headimg":"https://cdn.jsdelivr.net/gh/doflake/Picture/Posts/doflake-document/HeadImg.jpg","_content":"","source":"_posts/[doflake] 主题文档 - 副本 (5).md","raw":"---\ntitle: '【Doflake】 主题文档'\nmathjax: true\ndate: 2021-03-10 20:02:26\nlink_c: Doflake\nlink_name: Document\ntop:\nheadimg: https://cdn.jsdelivr.net/gh/doflake/Picture/Posts/doflake-document/HeadImg.jpg\n---\n","slug":"[doflake] 主题文档 - 副本 (5)","published":1,"updated":"2021-05-11T06:56:35.983Z","comments":1,"layout":"post","photos":[],"link":"","_id":"ckol9ou6x0006d0avblbrheqj","content":"","site":{"data":{}},"excerpt":"","more":""},{"title":"【Doflake】 主题文档","mathjax":true,"date":"2021-03-10T12:02:26.000Z","link_c":"Doflake","link_name":"Document","top":null,"headimg":"https://cdn.jsdelivr.net/gh/doflake/Picture/Posts/doflake-document/HeadImg.jpg","_content":"","source":"_posts/[doflake] 主题文档 - 副本 (8).md","raw":"---\ntitle: '【Doflake】 主题文档'\nmathjax: true\ndate: 2021-03-10 20:02:26\nlink_c: Doflake\nlink_name: Document\ntop:\nheadimg: https://cdn.jsdelivr.net/gh/doflake/Picture/Posts/doflake-document/HeadImg.jpg\n---\n","slug":"[doflake] 主题文档 - 副本 (8)","published":1,"updated":"2021-05-11T06:56:35.983Z","comments":1,"layout":"post","photos":[],"link":"","_id":"ckol9ou6x0007d0av9ls1cpwj","content":"","site":{"data":{}},"excerpt":"","more":""},{"title":"【Doflake】 主题文档","mathjax":true,"date":"2021-03-10T12:02:26.000Z","link_c":"Doflake","link_name":"Document","top":null,"headimg":"https://cdn.jsdelivr.net/gh/doflake/Picture/Posts/doflake-document/HeadImg.jpg","_content":"","source":"_posts/[doflake] 主题文档 - 副本.md","raw":"---\ntitle: '【Doflake】 主题文档'\nmathjax: true\ndate: 2021-03-10 20:02:26\nlink_c: Doflake\nlink_name: Document\ntop:\nheadimg: https://cdn.jsdelivr.net/gh/doflake/Picture/Posts/doflake-document/HeadImg.jpg\n---\n","slug":"[doflake] 主题文档 - 副本","published":1,"updated":"2021-05-11T06:56:35.983Z","comments":1,"layout":"post","photos":[],"link":"","_id":"ckol9ou6y0008d0av03s8e9up","content":"","site":{"data":{}},"excerpt":"","more":""},{"title":"【Doflake】 主题文档","mathjax":true,"date":"2021-03-10T12:02:26.000Z","link_c":"Doflake","link_name":"Document","top":null,"headimg":"https://cdn.jsdelivr.net/gh/doflake/Picture/Posts/doflake-document/HeadImg.jpg","_content":"","source":"_posts/[doflake] 主题文档.md","raw":"---\ntitle: '【Doflake】 主题文档'\nmathjax: true\ndate: 2021-03-10 20:02:26\nlink_c: Doflake\nlink_name: Document\ntop:\nheadimg: https://cdn.jsdelivr.net/gh/doflake/Picture/Posts/doflake-document/HeadImg.jpg\n---\n","slug":"[doflake] 主题文档","published":1,"updated":"2021-05-12T09:09:43.413Z","comments":1,"layout":"post","photos":[],"link":"","_id":"ckol9ou6y0009d0avaz8jgk7q","content":"","site":{"data":{}},"excerpt":"","more":""}],"PostAsset":[],"PostCategory":[],"PostTag":[],"Tag":[]}}